<?xml version="1.0" encoding="UTF-8" standalone="yes"?>
<menu>
	
	<menu>
		<title>300</title>
		<microhd>1U6vHES9aSFKEEuhGuZ9fu0qz99tnofQI</microhd>
		<fullhd>1U6vHES9aSFKEEuhGuZ9fu0qz99tnofQI</fullhd>
		<tresd>NA</tresd>
		<cuatrok>1U6vHES9aSFKEEuhGuZ9fu0qz99tnofQI</cuatrok>
		<thumbnail>https://image.tmdb.org/t/p/original/lGv19gokQvgC7jgjWqapIachnxU.jpg</thumbnail>
		<fanart>https://image.tmdb.org/t/p/original/lgBZlJ1LHQel5nneNQMoesmvc7l.jpg</fanart>
		<date>2006</date>
		<genre>Acción. Bélico. Aventuras. Fantástico</genre>
		<extra>Mis</extra>
		<info>Adaptación del cómic de Frank Miller (autor del cómic 'Sin City') sobre la famosa batalla de las Termópilas (480 a.C.). El objetivo de Jerjes, emperador de Persia, era la conquista de Grecia, lo que desencadenó las Guerras Médicas. Dada la gravedad de la situación, el rey Leónidas de Esparta (Gerard Butler) y 300 espartanos se enfrentaron a un ejército persa que era inmensamente superior.</info>
	</menu>	
	<menu>
         <title>[COLOR white]- Capitulo [/COLOR][B][COLOR red] :[/COLOR][/B]</title>
         <thumbnail>nolink</thumbnail>
         <fanart>nolink</fanart>
         <urlsolve>https://drive.google.com/file/d/1U6vHES9aSFKEEuhGuZ9fu0qz99tnofQI/view</urlsolve>
   </menu>
   <menu>
         <title>[COLOR white]- Capitulo [/COLOR][B][COLOR red] :[/COLOR][/B]</title>
         <thumbnail>nolink</thumbnail>
         <fanart>nolink</fanart>
         <urlsolve>https://drive.google.com/file/d/1dh7mflPCx-yAhk3wCmlo_FWW5q5NsjQ_/view?usp=sharing</urlsolve>
   </menu>
</menu>

<!-- https://drive.google.com/file/d/1dh7mflPCx-yAhk3wCmlo_FWW5q5NsjQ_/view?usp=sharing

h ttps://drive.google.com/uc?export=download&id= -->

<!-- https://drive.google.com/file/d/1U6vHES9aSFKEEuhGuZ9fu0qz99tnofQI/view?usp=drive_link

https://drive.google.com/file/d/1U6vHES9aSFKEEuhGuZ9fu0qz99tnofQI/view -->